flowno/__init__.py
flowno/core/__init__.py
flowno/core/flow_hdl.py
flowno/core/flow_hdl_view.py
flowno/core/group_node.py
flowno/core/mono_node.py
flowno/core/node_base.py
flowno/core/streaming_node.py
flowno/core/types.py
flowno/core/event_loop/__init__.py
flowno/core/event_loop/commands.py
flowno/core/event_loop/event_loop.py
flowno/core/event_loop/instrumentation.py
flowno/core/event_loop/primitives.py
flowno/core/event_loop/queues.py
flowno/core/event_loop/selectors.py
flowno/core/event_loop/synchronization.py
flowno/core/event_loop/tasks.py
flowno/core/event_loop/types.py
flowno/core/flow/__init__.py
flowno/core/flow/flow.py
flowno/core/flow/instrumentation.py
flowno/core/flow/primitives.py
flowno/core/flow/types.py
flowno/decorators/__init__.py
flowno/decorators/multiple_output.py
flowno/decorators/node.py
flowno/decorators/node_meta_multiple_dec.py
flowno/decorators/node_meta_single_dec.py
flowno/decorators/single_output.py
flowno/decorators/wrappers.py
flowno/io/__init__.py
flowno/io/headers.py
flowno/io/http_client.py
flowno/io/http_server.py
flowno/utilities/__init__.py
flowno/utilities/asyncgen_wrapper.py
flowno/utilities/coroutine_wrapper.py
flowno/utilities/helpers.py
flowno/utilities/logging.py
flowno-0.1.13.dist-info/licenses/LICENSE
flowno-0.1.13.dist-info/METADATA
flowno-0.1.13.dist-info/WHEEL
flowno-0.1.13.dist-info/top_level.txt
flowno-0.1.13.dist-info/RECORD
