Metadata-Version: 2.4
Name: flowno
Version: 0.1.13
Summary: A Python DSL for writing dataflow programs.
Author-email: Tyler Parker <tparker@computemachines.com>
License: MIT
Project-URL: Homepage, https://flowno.net
Project-URL: Documentation, https://flowno.net/docs
Project-URL: Repository, https://github.com/computemachines/flowno
Project-URL: Issues, https://github.com/computemachines/flowno/issues
Keywords: dataflow,dsl,python
Classifier: Development Status :: 3 - Alpha
Classifier: Intended Audience :: Developers
Classifier: Topic :: Software Development :: Libraries
Classifier: License :: OSI Approved :: MIT License
Classifier: Programming Language :: Python :: 3
Classifier: Programming Language :: Python :: 3.10
Classifier: Programming Language :: Python :: 3.11
Classifier: Programming Language :: Python :: 3.12
Classifier: Programming Language :: Python :: 3.13
Requires-Python: >=3.10
License-File: LICENSE
Requires-Dist: typing-extensions
Requires-Dist: docopt
Dynamic: license-file
